aws_cdk_github_oidc/__init__.py
aws_cdk_github_oidc/py.typed
aws_cdk_github_oidc/_jsii/__init__.py
aws_cdk_github_oidc/_jsii/aws-cdk-github-oidc@2.4.1.jsii.tgz
aws_cdk_github_oidc-2.4.1.dist-info/LICENSE
aws_cdk_github_oidc-2.4.1.dist-info/METADATA
aws_cdk_github_oidc-2.4.1.dist-info/WHEEL
aws_cdk_github_oidc-2.4.1.dist-info/top_level.txt
aws_cdk_github_oidc-2.4.1.dist-info/RECORD
