Metadata-Version: 2.1
Name: aws-cdk-github-oidc
Version: 2.4.1
Summary: CDK constructs to use OpenID Connect for authenticating your Github Action workflow with AWS IAM
Home-page: https://github.com/aripalo/aws-cdk-github-oidc.git
Author: Ari Palo<opensource@aripalo.com>
License: Apache-2.0
Project-URL: Source, https://github.com/aripalo/aws-cdk-github-oidc.git
Classifier: Intended Audience :: Developers
Classifier: Operating System :: OS Independent
Classifier: Programming Language :: JavaScript
Classifier: Programming Language :: Python :: 3 :: Only
Classifier: Programming Language :: Python :: 3.7
Classifier: Programming Language :: Python :: 3.8
Classifier: Programming Language :: Python :: 3.9
Classifier: Programming Language :: Python :: 3.10
Classifier: Programming Language :: Python :: 3.11
Classifier: Typing :: Typed
Classifier: Development Status :: 4 - Beta
Classifier: License :: OSI Approved
Requires-Python: ~=3.7
License-File: LICENSE
Requires-Dist: aws-cdk-lib (<3.0.0,>=2.89.0)
Requires-Dist: constructs (<11.0.0,>=10.0.0)
Requires-Dist: jsii (<2.0.0,>=1.86.1)
Requires-Dist: publication (>=0.0.3)
Requires-Dist: typeguard (~=2.13.3)
